{"name": "刘以达 Tats Lau", "intro": "刘以达，香港音乐创作人、演员。他曾在摇滚吉他比赛中获奖，在1980年组成他的首支乐队DLLM。于1985年与歌手黄耀明组成乐队“达明一派”，在香港非主流音乐界影响深远。 1990年，逹明一派拆伙，刘以达曾先后成立“刘以达与梦”、“刘以达官立小学”等组合，并于1996年推出个人専辑《麻木》。除此之外，他亦有作曲和替电影配乐，凭《诱僧》荣获第三十届金马奖最佳电影配乐。从九十年代中后期开始，刘以达参与多部电影幕前演出，尤擅于演绎冷面笑匠的角色，代表作有《大内密探零零发》中的“保龙一族情报人员”、《食神》中的“梦遗大师”等，他在《大内密探零零发》的“情报人员”精彩扮演至今让人忍俊不住。其他作品有《安娜与武林》、《绝世好宾》等。", "pictures_index": "https://img9.doubanio.com/view/celebrity/s_ratio_celebrity/public/p24656.webp", "sex": "男", "star": "双鱼座", "birthday": "1963-02-23", "birthplace": "中国香港", "url": "/celebrity/1034328/"}