{"name": "哈里森·福特 Harrison Ford", "intro": "哈里森·福特1942年出生在伊利诺州支加哥市，父亲为爱尔兰天主教徒，母亲是俄籍犹太人。1973年演出《美国风情画》，从此带来好运，日后被卢卡斯选为《星球大战》男主角，自此塑造了银幕超级英雄形象。1981年，福特接演了由斯蒂文·斯皮尔伯格导演、卢卡斯担任制片的《夺宝奇兵》(Raiders of the Lost Ark)。这部冒险片获得了非比寻常的成功，不但成为电影史上最卖座的电影之一，也得到各方好评，英雄印第安纳·琼斯这个名字和哈里森·福特再也分不开了。他也因此名垂影史。 哈里森·福特出演过的影片中有7部在电影票房史上创下最高记录。1985年因电影《目击者》获得奥斯卡最佳演员提名。因1995年的《情归巴黎》，1993年的《亡命天涯》，1986年的《蚊子海岸》，1985年的《目击者》获得当年度的金球奖提名。", "pictures_index": "https://img9.doubanio.com/view/celebrity/s_ratio_celebrity/public/p1452760482.06.webp", "sex": "男", "star": "巨蟹座", "birthday": "1942-07-13", "birthplace": "美国,伊利诺伊州,芝加哥", "url": "/celebrity/1009238/"}