{"name": "理查德·哈里斯 Richard Harris", "intro": "他是一名磨房老板的儿子，长大后曾在英国皇家学院，接受音乐及戏剧课程的训练。1956年首次登台演戏，两年后即步入英国电影界。1963年在《超级的男性》中，饰演一名粗暴的橄榄球员，勇夺戛纳电影节最佳男主角奖，从此获得国际性的知名度。1967年主演了他最著名的一部歌舞电影《凤宫劫美录》，饰演的亚瑟王又演又唱，影坛还无人能出其右。其后他在娱乐圈作多线发展，既演出《太阳盟》等商业性浓厚的暴力西部片，又大唱《麦克亚瑟公园》等高调的流行曲出版个人专辑唱片，甚至写诗和写小说。近年来以性格演员姿态参与多部名片演出，包括：《爱国者游戏》、《杀无赦》及最新的《角斗士》等。值得一提的是，他还参与扮演了《哈利波特》系列电影前两部《哈利波特与魔法石》和《哈利波特与密室》中的阿不思·邓不利多校长，也是哈里斯的绝唱。 伦敦时间2002年10月25日晚7时在伦敦的一所医院中病逝，享年72岁。", "pictures_index": "https://img9.doubanio.com/view/celebrity/s_ratio_celebrity/public/p10555.webp", "sex": "男", "star": "天秤座", "birthday": "", "birthplace": "爱尔兰,Limerick", "url": "/celebrity/1027172/"}