{"name": "劳拉·哈灵 Laura Harring", "intro": "劳拉·哈灵，美国演员。母亲是心理治疗师，父亲是有机农民。1971年的两次离婚。 1985年，她成为第一位拉美裔赢得美国小姐桂冠，并连续5德克萨斯优胜者第一。她还做出了在1985年环球小姐选美大赛的前10名。哈灵在亚洲旅行，游览欧洲和印度作为一个社会工作者的工作。它在欧洲时，她被介绍给世界的贵族，并在1987年，她嫁给了伯爵卡尔爱德华冯俾斯麦- Schönhausen，千秋万奥托冯俾斯麦的孙子。虽然她保留了伯爵夫人冯俾斯麦- Schönhausen，于1989年离婚，但仍保持朋友的情侣称号。哈灵学戏剧在表演艺术学院和伦敦是在意大利的即兴喜剧的风格，以及拉丁舞，其中包括阿根廷探戈的技能。", "pictures_index": "https://img1.doubanio.com/view/celebrity/s_ratio_celebrity/public/p5008.webp", "sex": "女", "star": "双鱼座", "birthday": "1964-03-03", "birthplace": "墨西哥,锡那罗亚,洛斯莫奇斯", "url": "/celebrity/1031883/"}