{"name": "失翼灵雀 Skrivánci na niti", "actors": [["/celebrity/1100522/", "鲁道夫·霍辛斯基"], ["/celebrity/1037759/", "伏拉基米尔·布劳德斯基"], ["/celebrity/1135794/", "瓦茨拉夫·内茨卡"]], "introduction": "捷克“胜利二月”后的一处废铁回收厂里，因宗教信仰不愿在周日工作的厨师帕维尔（Václav Neckár 饰）与检察官、哲学教授、奶牛场主等人组成的一只劳动小组正在罢工，昔日工人、如今他们的头头奉命带领一支剧组来这里拍摄宣传电影，导演获悉罢工后拂袖而去，但这次拍摄却把帕维尔和在附近劳改的美丽女犯基塔（Jitka Zelenohorská 饰）的手牵到了一起。贸易协会派人劝解罢工，反被奶牛场主反诘，而奶牛场主也至此不知所踪。同时看管女犯的法警结婚了，而工人们只能唠着哲学与艺术的话题偷窥女犯人们。不久少先队员来访，教授质问带队的辅导员，结果他也不知去向了。基塔终于答应了帕维尔的求婚，两人进行了一场缺席婚礼，最后大领导视察地区工作，帕维尔向他提出了跟教授一样的问题…… 本片遭禁21年后获1990年柏林金熊奖、国际影评人费比西奖。", "pictures_index": "https://img3.doubanio.com/view/photo/s_ratio_poster/public/p2503999630.webp", "state": " 捷克斯洛伐克", "language": " 捷克语", "length": "94 分钟", "comments": ["闵采尔在冷静里发问，社会主义能带来什么。“这个社会将会把你像钢铁一样融掉”，这不是对社会主义工业化的最大预言吗。当面对家里的五个儿女，当面对新娘缺席的爱情，当我们在轰鸣声中讨论哲学，什么更重要，集体的发展，还是个人的尊严？", "在723事件之后非常应景儿的片子，发生在五十年代捷克一党专制，空谈主义，好大喜功的社会环境下，被迫改造的资产阶级知识分子的辛涩生活。贯穿始终的废墟布景和泛暖含蓄的感情戏的强烈反差是最打动我的地方。投射在面孔上的一方明媚，聚拢在一起的羞涩的手，以及片尾那头顶的一方光明，细节精致如斯。", "捷克也有“大炼钢铁”，门泽尔改编赫拉巴尔，处处嘲讽。布景一流。后冷战降临之时的第一批东欧名作。", "社会主义大山下的小幸福", "1984+美丽新世界+布拉格之恋，鲁道夫·霍辛斯基的每次表演都是咄咄逼人！"]}