{"name": "血肉之躯 Warm Bodies", "actors": [["/celebrity/1036341/", "尼古拉斯·霍尔特"], ["/celebrity/1031836/", "泰莉莎·帕尔墨"], ["/celebrity/1041013/", "约翰·马尔科维奇"], ["/celebrity/1017991/", "戴夫·弗兰科"], ["/celebrity/1268721/", "安娜丽·提普顿"], ["/celebrity/1006978/", "罗伯·考德瑞"], ["/celebrity/1040665/", "科里·哈德里克"]], "introduction": "他（尼古拉斯·霍尔特 Nicholas Hoult 饰）是一只生活在末世的僵尸，依稀只记得自己的名字里有个“R”。与世俗观念不同，作为僵尸他能够思考，依旧残存着些许生前记忆。R生活在废弃的班机上，喜欢收集唱片和饰品，除了吃人外似乎与常人没有两样。这一日，R和僵尸好友们外出觅食，期间遭遇一伙从隔离区来到污染区搜寻药品的人类。在残忍吞噬青年佩里（戴夫·弗兰科 Dave Franco 饰）的大脑后，R拥有了对方的记忆，由此也对和佩里同行而来的女孩朱莉（泰莉莎·帕尔墨 Teresa Palmer 饰）产生恻隐与好感。他将女孩带回自己的住地，通过数日的相处渐渐取得对方的信任，而美丽的朱莉也让R找回作为人类久违的温暖和复杂情感…… 本片根据艾萨克·马里昂（Isaac Marion）的同名小说改编。", "pictures_index": "https://img3.doubanio.com/view/photo/s_ratio_poster/public/p1828783542.webp", "state": " 美国 / 加拿大", "language": " 英语", "length": "98分钟", "comments": ["观众的高度赞扬才是笑点", "好在设定上，尤其开头那段自我调侃，有一种冷幽默在里面。不过之后仅是讲一个爱情故事又有点太无趣了，比如让僵尸学开车远没有让人学僵尸更有趣。人物关系仍是罗密欧与朱丽叶式的。尤其是后面还有阳台的那场戏，真是与罗密欧如出一辙", "这片子比想象中搞笑很多很多啊，所有人都在不停地卖萌，一脸血！尼古拉斯霍特这个角色真是太蠢萌啦啊啊啊！硬要跟暮光比的话，既然都是爱情片，那弄得可爱搞笑点自然讨人喜欢多了。女主挺好看，但有些角度神似暮光女，大概这种相貌真的适合演青春片。", "开创僵尸类型片的浪漫爱情先河！非常愉悦的观影经验，意料之外的诙谐有趣，配乐相当出色。原来是罗密欧和朱丽叶！", "男主情窦初开的内心独白可爱到爆，女主有点绿茶婊。主打是各种萌呆的温暖牌僵尸，设定荒诞又治愈。爱情歌曲作为推动情节的重要线索从头串烧到尾，原声一定要收藏！！！"]}