{"name": "活跳尸 Re-Animator", "actors": [["/celebrity/1049736/", "杰弗瑞·考姆斯"], ["/celebrity/1055060/", "布鲁斯·艾伯特"], ["/celebrity/1014139/", "芭芭拉·克兰普顿"], ["/celebrity/1028215/", "大卫·盖尔"], ["/subject_search?search_text=Robert%20Sampson", "Robert Sampson"]], "introduction": "瑞典密斯科汤尼克医学院，年轻的学生肯恩（Bruce Abbott 饰）和院长的女儿梅根（Barbara Crampton 饰）暗中相恋，两人相约在肯恩毕业后正式结婚。 不久，天才医师赫伯特•韦斯特（Jeffrey Combs 饰）自澳大利亚归来。在澳期间，他曾与另一位科学家研究一种令死者复活的药物，但该药物的副作用是复活后的人皆丧失心智，失性狂乱，他的研究伙伴即在一场事故中丧生。韦斯特找到肯恩的公寓，希望与之合租。他始终不忘复活药物的研究，并争取到肯恩的帮助。然医学院院长却因韦斯特在澳洲的事故而禁止相关研究，最终酿成一起惨案。 另一方面，与韦斯特针锋相对希尔教授（David Gale 饰）也觊觎着这项惊世研究……", "pictures_index": "https://img9.doubanio.com/view/photo/s_ratio_poster/public/p1682645836.webp", "state": " 美国", "language": " 英语 / 德语", "length": "86分钟(未删减版)", "comments": ["算是小时候的启蒙恐怖片了，就记得故事又恐怖又好笑，非常符合小孩子的世界观#我一直觉得恐怖片才是最适合给小孩子看的电影#", "除了各种给力的血浆喷射和烂肉横飞，第一部在调度、气氛、叙事和人物性格方面都是最好的。贯穿始终的绿色荧光液体是关键恐怖点，和深闺疑云里闪闪发光的牛奶杯有异曲同工之妙。当然，配乐也基本就是抄的惊魂记，没少向希胖偷师。", "小时和表姐一起看的，我看得欢乐，表姐恶心得饭都不敢吃。。PS：VCD打码", " 第一部.   教授是坏的,  男主的女友也变异了.  赫伯特逃跑 了.", "1.脑袋可以遥控身体；2.活尸不穿衣服真是恶心；3.那娘们是个SB，居然站在电梯门口；4.配乐很经典"]}