{"name": "国际市场 국제시장", "actors": [["/celebrity/1051046/", "黄政民"], ["/celebrity/1102505/", "金允珍"], ["/celebrity/1203077/", "吴达洙"], ["/celebrity/1170566/", "张荣男"], ["/celebrity/1029108/", "郑镇荣"], ["/celebrity/1329322/", "罗美兰"], ["/celebrity/1326766/", "金瑟祺"], ["/celebrity/1275637/", "郑允浩"], ["/celebrity/1348581/", "Stella Choe"]], "introduction": "朝鲜战争期间，少年尹德秀随同父母登上美军的救援船，却遭遇了毕生难忘的生离死别。战火虽然停息，南北半岛则一分为二，饱受炮火荼毒的北方故乡遥不可及。长大之后，代替父亲成为顶梁柱的德秀（黄政民 饰）努力赚钱，为了筹备弟弟妹妹的学费，他和童年好友千达九（吴达洙 饰）前往西德当起了矿工。万里家国，乡愁如缕，孤独的德秀偶然邂逅在德国念护士专业的韩国女孩英子（金允珍 饰），从此黑若煤炭的生活照进了灿烂光芒。快乐的时光与死亡的磨难如影随形，好在在经历了生死考验之后，德秀回到朝思暮想的家中，并赢得了英子的芳心。 漫长而坎坷的人生路，德秀在妻子、亲朋的陪伴下艰难前行……", "pictures_index": "https://img1.doubanio.com/view/photo/s_ratio_poster/public/p2210568759.webp", "state": " 韩国", "language": " 韩语 / 英语 / 德语", "length": "126分钟", "comments": ["一个人要走多远的路，才能从一个男孩变成男人。从朝鲜到韩国，从韩国到德国，再回到韩国，再从韩国到越南。一个家族的变迁，一个时代的巨变，一个男人的担当。勾画了一个个岁月的变迁。大时代有巨变，小细节有温馨，爱，是唯一的答案。", "中文片名太奇怪了- -海云台导演新片，还是大动乱小人物，格局更广了：从童年拍到迟暮，历经朝鲜战争、矿工护士赴德、越南战争，万人特效场面，半部近代史...韩国人在苦情催泪和喜闹剧上已经驾轻就熟，而且居然能无缝转换。柏林好多老外抽泣，年度第一催泪弹，不哭都难，一大家配角也都不错，观赏性强", "韩国票房冠军电影也不咋样，流水账叙事，要是没有最后几场煽情戏只值两星。", "人生能得一手足兄弟，又有心爱姑娘相伴，此生无憾。", "泪崩了，在办公室哭成傻缺，面壁去"]}