{"name": "处子之山 Fúsi", "actors": [["/celebrity/1355532/", "贡纳·永松"], ["/celebrity/1308865/", "伊尔穆尔·克里斯蒂安·斯多蒂尔"], ["/celebrity/1110972/", "Sigurjón Kjartansson"], ["/celebrity/1109595/", "Margrét Helga Jóhannsdóttir"], ["/celebrity/1356524/", "Franziska Una Dagsdóttir"], ["/celebrity/1106340/", "Arnar Jónsson"], ["/celebrity/1356525/", "Thorir Sæmundsson"], ["/celebrity/1356526/", "Þorsteinn Gunnarsson"], ["/celebrity/1182458/", "Friðrik Friðriksson"], ["/celebrity/1356527/", "Walter Grímsson"]], "introduction": "已过不惑之年的单身狗Fúsi 是一个机场搬运工 精通机械却不善言辞 他的生活单调到除了工作就是金属乐，各种模型手办 在家人的鼓动下他尝试去了一个舞蹈班并终于认识了妹子 但害羞怯懦的他最后能走出自己的世界吗", "pictures_index": "https://img1.doubanio.com/view/photo/s_ratio_poster/public/p2331815937.webp", "state": " 冰岛 / 丹麦", "language": " 冰岛语", "length": "94分钟", "comments": ["到哪里找到整整一部电影里所有的那么不好看的演员，就像我们的生活一模一样！", "4.5 感同身受.觉得Fusi其实是个沟通高手,他能清晰表达需求,而非闭嘴自责再怪别人伤害自己.这点我要尽力做到.一个自足之人拥有爱好,保持自尊,不伤害.不评价.是极高的境界.正常人不能容忍他的“不同”,同化不了就迁怒,或许是出于对他纯粹人生的嫉妒.他爱她,便已让他有所得.她留给他的勇气就是最好的礼物.", "等飞机时看的，后来却完全遗忘晚点三小时的事情。节奏确实比较沉闷缓慢，但却与整体片子风格非常吻合。一个隐藏在丑陋皮囊下的美丽灵魂，可惜的是，在这个“颜值即是正义”的时代，又有多少人愿意了解灵魂的美丽，而又多么唾弃皮囊的丑陋。福斯不是悲悯的圣人，他只是一个凡人。敬温柔相待。", "不是坏人不是怪更不会是性变态，喜欢手办爱二战能修汽车会做饭。你给我希望也让我失望，一人游埃及会有新爱情。", "终究还是一个人去埃及，终究还是一个人看电影"]}