{"name": "两杆大烟枪 Lock, Stock and Two Smoking Barrels", "actors": [["/celebrity/1027179/", "杰森·弗莱明"], ["/celebrity/1007028/", "德克斯特·弗莱彻"], ["/celebrity/1014074/", "尼克·莫兰"], ["/celebrity/1049484/", "杰森·斯坦森"], ["/celebrity/1048187/", "斯蒂文·麦金托什"], ["/celebrity/1027320/", "斯汀"], ["/celebrity/1013804/", "维尼·琼斯"]], "introduction": "艾迪（尼克·莫伦）思维敏捷，是个玩牌高手。在三个好友的支持下，艾迪携巨资参加了黑社会的高额赌局，不想落入圈套，欠下50万的赌债。为了还清赌债，艾迪和朋友们绞尽脑汁，最终算计到一群毒贩身上，并为打劫购买了两杆老式烟枪。 不想这群不安分的毒贩，正惦念着他们毒品供应商的钱，并在同一天实施了打劫。在毒贩们费尽周折，把毒品供应商熨的整整齐齐的钱款拿到手后，艾迪他们幸运的坐享其成。可是他们不知道，这看似简单的抢劫案背后，更有厉害的角色参与其中。他们手里的两杆破烟枪也隐藏着不少故事。 在无知与莽撞中置身漩涡的他们能侥幸脱身么？笑料迭出的偶发事件里，穿插着小人物与大人物的辛酸幽默。", "pictures_index": "https://img1.doubanio.com/view/photo/s_ratio_poster/public/p792443418.webp", "state": " 英国", "language": " 英语", "length": "107分钟", "comments": ["中国多少年轻导演在学这风格", "大轮回剧情，赞不绝口。配乐无比踩点。特写连毛孔胡渣都分毫毕现。摇摇欲坠，坐在各种笑料回荡的嘴角上，寻着被烟熏的发黄的咯吱作响的牙齿，就快要从这口腔中滑落下去。笑到背气的是帅哥那严峻，放纵时而又苦逼崩溃的脸。铤而走险后疯癫狂欢，年轻人们决不会想到这一切都只是纠葛的开始。", "从此开始喜欢上英伦范儿。我真的是太喜欢这部电影鸟。", "疯狂的石头在他面前只是浮云", "你敢骗我，我就杀了你。如果你敢耍我，或者我认为你在耍我，我也杀了你。如果你忘了，我也会杀了你。事实上你要很努力才能保住小命，我说的话你听懂了没有？因为如果你不懂，我就杀了你。"]}