{"name": "斯坦利·图齐 Stanley Tucci", "intro": "史坦利·图齐，1960年11月11日在纽约州出生，是意大利裔美国人。高中时他开始对演戏感兴趣并参加了学校的戏剧俱乐部，他于纽约州立大学（S.U.N.Y.）Purchase分校毕业。1982年开始在百老汇舞台上崭露头角，在那之后便在一系列或大或小的电影或者电视剧里出演角色。他最为人熟知的角色包括《穿普拉达的女王》里的时装编辑以及《可爱的骨头》的变态杀人犯。他的标志是能为电影角色自如地变化声音、发型等等体型特征。 他和前妻结婚14年共同抚育3个孩子，直至2009年前妻因乳腺癌去世。他在2011年11月与菲丽西提·布朗特（与史坦利·图齐在《穿普拉达的女王》里合作过的Emily Blunt的姐姐）订婚。", "pictures_index": "https://img3.doubanio.com/view/celebrity/s_ratio_celebrity/public/p26071.webp", "sex": "男", "star": "天蝎座", "birthday": "1960-11-11", "birthplace": "美国,纽约,皮克斯基尔", "url": "/celebrity/1040517/"}