{"name": "理查德·格雷弗斯 Richard Griffiths", "intro": "理查德·格雷弗斯（Richard Griffiths），1947年7月31日在英国出生。他是一位以扮演莎士比亚戏剧中的丑角而闻名于现代与古典舞台的演员。在一生的大部分时间里，理查德·格雷弗斯扮演亨利三世。他的父母都是聋哑人，所以在很小的时候他就学习了手势语，表现出极大的表演天赋。 在《哈利波特》系列影片中，理查德·格里菲斯饰演收留男主角哈利·波特的姨丈弗农·德思礼（Vernon Dursley），这个大胖子和家人联手欺负哈利·波特的场景，恐怕让很多影迷都印象深刻。此外，理查德·格里菲斯还出演过影片《高校男生》（The History Boys）和《我与长指甲》（Withnail And I）。 由于拍摄《哈利波特》，理查德·格里菲斯曾与饰演哈利·波特的丹尼尔·雷德克里夫（Daniel Radcliffe）有过很长时期的合作，后者对他也有着极高的赞誉：“在我职业生涯最重要的两个阶段，理查德都在我身边。2000年8月，也就是《哈利波特》正式开拍前，我们曾试拍过这部电影的小短片，当时我非常紧张，正是他让我放松下来。7年后我们又合作了舞台剧《恋马狂》（Equus），首次表演舞台剧的我也非常紧张，正是在他的疏导下，我才觉得这项工作充满了乐趣。” 理查德·格里菲斯曾因为出色的表演才华而被授予大英帝国官佐勋章（OBE）。2013年，理查德·格里菲斯因心脏手术并发症于当地时间28日不治去世，享年65岁。他去世的地点是在考文垂和沃里克郡大学医院（University Hospital of Coventry and Warwickshire）。", "pictures_index": "https://img1.doubanio.com/view/celebrity/s_ratio_celebrity/public/p1484903562.7.webp", "sex": "男", "star": "狮子座", "birthday": "", "birthplace": "英国,克利夫兰", "url": "/celebrity/1025262/"}