{"name": "铃木杏 Anne Suzuki", "intro": "铃木杏，日本女演员。2006年，从东京堀越高 铃木杏等学校毕业，高中三年与长泽雅美同班，两人私交很好。现在和光大学（Wako.University）现代人间学系在学中。在演艺圈早期以拍摄广告为主，1996年接演日剧《金田一少年事件簿特别版》正式在电视戏剧界出道，之后还演过《青鸟》、《夜逃屋本铺》等多部脍炙人口的日剧。1999年开始进军大银幕，2002年与 金城武合演科幻电影《武者回归》，年纪虽小，但是自然不生涩的演技让她获奖无数。已在台湾上映的动画片《蒸汽男孩》由她担纲主角的配音；由《 无间道 》导演刘伟强执导，改编自日本知名动漫画的《头文字D》也是看上她在日本的高人气，热情邀请她共同演出，与 周杰伦、陈冠希、黄秋生等当红帅哥、艺人演对手戏。", "pictures_index": "https://img1.doubanio.com/view/celebrity/s_ratio_celebrity/public/p6547.webp", "sex": "女", "star": "金牛座", "birthday": "1987-04-27", "birthplace": "日本,东京", "url": "/celebrity/1045413/"}