{"name": "安德里亚·罗斯 Andrea Roth", "intro": "Andrea Roth (born September 30, 1967) is a Canadian actress. She is perhaps best known for her roles as Janet Gavin, the wife of main character Tommy Gavin, on the FX television series Rescue Me (2004–2011), as Victoria Chase in The Collector (2009), and before that, as Diana Powers/NeuroBrain in RoboCop: The Series (1994).", "pictures_index": "https://img3.doubanio.com/view/celebrity/s_ratio_celebrity/public/p47190.webp", "sex": "女", "star": "天秤座", "birthday": "1967-09-30", "birthplace": "加拿大,安大略省,伍德斯托克", "url": "/celebrity/1138362/"}