{"name": "爵士春秋 All That Jazz", "actors": [["/celebrity/1041132/", "罗伊·沙伊德尔"], ["/celebrity/1000091/", "杰西卡·兰格"], ["/celebrity/1133210/", "利兰·帕尔默"], ["/celebrity/1146135/", "安·赖因肯斯"], ["/celebrity/1098768/", "克里夫·戈曼"], ["/celebrity/1027963/", "本·沃伦"], ["/celebrity/1377924/", "伊丽莎白·福尔迪"], ["/celebrity/1037128/", "迈克尔·托兰"], ["/celebrity/1022813/", "马克斯·怀特"], ["/celebrity/1125982/", "威廉·勒马萨纳"]], "introduction": "本片是一部音乐歌舞片，集七十年代爵士乐之大成。在1980年第33届戛纳国际电影节上获得金棕榈奖，获52届奥斯卡（1979）最佳服装设计、最佳剪辑，最佳音乐三项金像奖。 ◇剧情介绍◇ 作为一个音乐剧迷，即使你不太熟悉金像奖导演Bob Fosse这个名字，我打赌你也一定听说过托尼奖和奥斯卡的大赢家《芝加哥》和《歌厅》，Fosse分别是这两部音乐剧电影版的编剧和导演，他的另一部著名作品就是这部《爵士春秋》。（其实只要稍微留意就可以从《芝加哥》的编舞上发现许多《爵士春秋》的影子，而且《芝加哥》开门见山的第一只曲子就是‘All That Jazz’。） 《爵士春秋》可称是Bob Fosse本人的半自传影片，片中的主人公是一位叫Joe Gideon的百老汇资深导演，他天马行空，我行我素，才华横溢，但是由于没有树立起远大的理想和正确的人生观和世界观，工作的压力和情...", "pictures_index": "https://img3.doubanio.com/view/photo/s_ratio_poster/public/p2192967650.webp", "state": " 美国", "language": " 英语 / 西班牙语", "length": "123分钟", "comments": ["直至北影节才迟迟看上，比《爱乐之城》喜欢不止一个量级。带着1970年代特有的阴暗色调和摇摇欲坠的城市气质，艺术生命也在2小时的虚实交替、梦境重叠、意乱情迷之间，从在女人烟酒中的纵欲挥霍，变成病床前的苟延残喘。在梳理舞台剧生意经同时，与演员、妻女、投资者的告别，也在欢歌中呈现悲剧效果。", "Roy Scheider举手投足把一个好色又有才华，娘气和傲气同在的歌舞剧大导演得淋漓尽致，舞台艺术极近华丽，美腿控必看！", "so sexy ！ so sad ！ so dreamy ！", "重刷，修复质量极佳。鲍勃·福斯，将形式主义推向极致的歌舞之王，醉生梦死、浮生若梦。", "这个版本是不是被剪切了？总之芝加哥绝对是抄袭这个爵士春秋的"]}